[
    {
        "id": 2569851246,
        "user": "armorvagyok",
        "title": "work in progress",
        "text": "been working on this for a couple of weeks",
        "tags": ["electronic", "future bass", "triplet"],
        "url": "https://soundcloud.com/tomarmor/rain-v4?si=f37a681508ee4d11b1fdce68e0b57fc0&utm_source=clipboard&utm_medium=text&utm_campaign=social_sharing"
    },
    {
        "id": 9181926981,
        "user": "armorvagyok",
        "title": "SOBER IS OUT",
        "text": "FINALLY",
        "tags": ["electronic", "melodic trap", "bass house"],
        "url": "https://youtu.be/dvK40X6PLVM?si=3CzBUpL_UwJBKOAk"
    }
]